ws_nexus_integration/__init__.py
ws_nexus_integration/_version.py
ws_nexus_integration/conftest.py
ws_nexus_integration/nexus_integration.py
ws_nexus_integration/tests/__init__.py
ws_nexus_integration/tests/test_nexus_integration.py
ws_nexus_integration-24.2.1.dist-info/LICENSE
ws_nexus_integration-24.2.1.dist-info/METADATA
ws_nexus_integration-24.2.1.dist-info/WHEEL
ws_nexus_integration-24.2.1.dist-info/entry_points.txt
ws_nexus_integration-24.2.1.dist-info/top_level.txt
ws_nexus_integration-24.2.1.dist-info/RECORD
