Metadata-Version: 2.1
Name: ws-nexus-integration
Version: 24.2.1
Summary: WS Nexus Integration
Home-page: https://github.com/whitesource-ps/ws-nexus-integration
Author: WhiteSource Professional Services
Author-email: ps@whitesourcesoftware.com
License: LICENSE
Classifier: Programming Language :: Python :: 3.7
Classifier: Programming Language :: Python :: 3.8
Classifier: Programming Language :: Python :: 3.9
Classifier: License :: OSI Approved :: Apache Software License
Classifier: Operating System :: OS Independent
Requires-Python: >=3.7
License-File: LICENSE
Requires-Dist: requests ~=2.31.0
Requires-Dist: wget ~=3.2
Requires-Dist: ws-sdk ==23.12.2
Requires-Dist: docker ~=6.1.3
Requires-Dist: setuptools ~=68.2.2
Requires-Dist: pytest ~=7.1.2
